{
  "users": [
    {
      "id": 1,
      "username": "Lizhao",
      "email": "asd@gmail.com",
      "password": "123456"
    },
    {
      "id": 2,
      "username": "Max",
      "email": "max@gmail.com",
      "password": "123456"
    },
    {
      "email": "sssss@gmail.com",
      "password": "ss",
      "username": "ss",
      "id": 3
    },
    {
      "email": "sssss@gmail.com",
      "password": "sss",
      "username": "sss",
      "id": 4
    },
    {
      "email": "18845356837@163.com",
      "password": "rzz4Jr!T2jdctQE",
      "username": "nd20629@bristol.ac.uk",
      "id": 5
    },
    {
      "email": "lizhaoliu97@gmail.com",
      "password": "SCg38h!@@whPQBX",
      "username": "sssss",
      "id": 6
    }
  ]
}